{
  "kind": "collectionType",
  "collectionName": "bkhk_active_users",
  "info": {
    "singularName": "bkhk-active-users",
    "pluralName": "bkhk-active-userss",
    "displayName": "Bkhk active users",
    "description": "bkhk-active-users collection type"
  },
  "options": {
    "draftAndPublish": true
  },
  "attributes": {
    "internalKey": {
      "type": "integer",
      "default": "0"
    },
    "username": {
      "type": "string",
      "default": "",
      "maxLength": 50
    },
    "lasthit": {
      "type": "integer",
      "default": "0"
    },
    "action": {
      "type": "string",
      "default": "",
      "maxLength": 255
    },
    "ip": {
      "type": "string",
      "default": "",
      "maxLength": 20
    }
  }
}
